django_react_admin/__init__.py
django_react_admin/management/__init__.py
django_react_admin/management/commands/build_react_admin.py
django_react_admin/migrations/__init__.py
django_react_admin/models.py
django_react_admin/src/.gitignore
django_react_admin/src/README.md
django_react_admin/src/package.json
django_react_admin/src/public/favicon.ico
django_react_admin/src/public/index.html
django_react_admin/src/public/logo192.png
django_react_admin/src/public/logo512.png
django_react_admin/src/public/manifest.json
django_react_admin/src/public/robots.txt
django_react_admin/src/src/App.css
django_react_admin/src/src/App.js
django_react_admin/src/src/App.test.js
django_react_admin/src/src/index.css
django_react_admin/src/src/index.js
django_react_admin/src/src/logo.svg
django_react_admin/src/src/serviceWorker.js
django_react_admin/src/src/users.js
django_react_admin/src/webpack.config.js
django_react_admin/src/yarn.lock
django_react_admin/static/__git__
django_react_admin/static/django_react_admin/asset-manifest.json
django_react_admin/static/django_react_admin/favicon.ico
django_react_admin/static/django_react_admin/index.html
django_react_admin/static/django_react_admin/logo192.png
django_react_admin/static/django_react_admin/logo512.png
django_react_admin/static/django_react_admin/manifest.json
django_react_admin/static/django_react_admin/precache-manifest.fb44c76e75461f39e1866aef37d0a4fa.js
django_react_admin/static/django_react_admin/robots.txt
django_react_admin/static/django_react_admin/service-worker.js
django_react_admin/static/django_react_admin/static/css/main.34de6062.chunk.css
django_react_admin/static/django_react_admin/static/css/main.34de6062.chunk.css.map
django_react_admin/static/django_react_admin/static/js/2.a5cf5eb4.chunk.js
django_react_admin/static/django_react_admin/static/js/2.a5cf5eb4.chunk.js.map
django_react_admin/static/django_react_admin/static/js/main.f9fe51be.chunk.js
django_react_admin-0.1.1.dist-info/WHEEL
django_react_admin-0.1.1.dist-info/METADATA
django_react_admin-0.1.1.dist-info/RECORD
