Metadata-Version: 2.1
Name: django-react-admin
Version: 0.1.1
Summary: 
Home-page: https://github.com/pawnhearts/django_react_admin
Author: ph
Author-email: robotnaoborot@gmail.com
Requires-Python: >=3.8,<4.0
Classifier: Programming Language :: Python :: 3
Requires-Dist: django (>=2.2,<3.0)
Requires-Dist: django-filter (>=2.2,<3.0)
Requires-Dist: djangorestframework (>=3.10,<4.0)
